MANIFEST.in
README.rst
setup.cfg
setup.py
PyLaz/PyLaz.py
PyLaz/__init__.py
PyLaz.egg-info/PKG-INFO
PyLaz.egg-info/SOURCES.txt
PyLaz.egg-info/dependency_links.txt
PyLaz.egg-info/top_level.txt