Metadata-Version: 1.1
Name: PyLaz
Version: 0.0.3
Summary: Python Library for Lazurite
Home-page: https://github.com/LAPIS-Lazurite/PyLaz
Author: lapis semiconductor
Author-email: lazurite@adm.lapis-semi.com
License: MIT
Keywords: Python library for Lazurite
Platform: UNKNOWN
Classifier: Development Status :: 4 - Beta
Classifier: Intended Audience :: Developers
Classifier: Topic :: Software Development :: Build Tools
Classifier: License :: OSI Approved :: MIT License
Classifier: Programming Language :: Python :: 2
Classifier: Programming Language :: Python :: 2.6
Classifier: Programming Language :: Python :: 2.7
Classifier: Programming Language :: Python :: 3
Classifier: Programming Language :: Python :: 3.3
Classifier: Programming Language :: Python :: 3.4
Classifier: Programming Language :: Python :: 3.5
